[
    {
    "id": "test000",
    "label": "Test 💎",
    "price": "1",
    "product": "Mobile Legends",
    "status": "active",
    "sp": 1
  },
  {
    "id": "13",
    "label": "78+8 💎",
    "price": "61.5",
    "product": "Mobile Legends",
    "status": "active",
    "sp": 61.5

  },
       {
    "id": "16642",
    "label": "Weekly Pass",
    "price": "140",
    "product": "Mobile Legends",
        "status": "active",
            "sp": 76


  },
    {
    "id": "23",
    "label": "156+16 💎",
    "price": "122",
    "product": "Mobile Legends",
    "status": "active",
        "sp": 122


  },
    {
    "id": "25",
    "label": "234+23 💎",
    "price": "177.5",
    "product": "Mobile Legends",
        "status": "active",
            "sp": 177.5


  },
    {
    "id": "25-13",
    "label": "343 💎",
    "price": "239",
    "product": "Mobile Legends",
        "status": "active",
            "sp": 239


  },
    {
    "id": "23-25",
    "label": "257+172 💎",
    "price": "5.78",
    "product": "Mobile Legends",
        "status": "active",
            "sp": 299.5


  },
     {
    "id": "25-25",
    "label": "257+257 💎",
    "price": "355",
    "product": "Mobile Legends",
        "status": "active",
            "sp": 355


  },
     {
    "id": "25-25-13",
    "label": "600 💎",
    "price": "416.5",
    "product": "Mobile Legends",
        "status": "active",
            "sp": 416.5


  },
     {
    "id": "26",
    "label": "625+81 💎",
    "price": "480",
    "product": "Mobile Legends",
        "status": "active",
            "sp": 480


  },
     {
    "id": "23-26",
    "label": "706+172 💎",
    "price": "604",
    "product": "Mobile Legends",
        "status": "active",
            "sp": 602


  },
      {
    "id": "23-23-26",
    "label": "937+112 💎",
    "price": "724",
    "product": "Mobile Legends",
        "status": "active",
            "sp": 724


  },
      {
    "id": "22593-22593",
    "label": "565+565 💎",
    "price": "1460",
    "product": "Mobile Legends",
    "status": "active",
        "sp": 770

  },
    {
    "id": "26-26",
    "label": "1412 💎",
    "price": "1749",
    "product": "Mobile Legends",
    "status": "active",
        "sp": 960

  },
    {
    "id": "22590",
    "label": "50+50 💎",
    "price": "75",
    "product": "Mobile Legends",
    "status": "active",
        "sp": 39

  },
     {
    "id": "22591",
    "label": "150+150 💎",
    "price": "238",
    "product": "Mobile Legends",
    "status": "active",
        "sp": 116.9

  },
       {
    "id": "22592",
    "label": "250+250 💎",
    "price": "339",
    "product": "Mobile Legends",
    "status": "active",
        "sp": 187.5

  },
        {
    "id": "22593",
    "label": "500+500 💎",
    "price": "729",
    "product": "Mobile Legends",
    "status": "active",
        "sp": 385

  },
  {
    "id": "ML3",
    "label": "3 💎",
    "price": "7",
    "product": "MLBB",
    "status": "active",
        "sp": 1

  },
  {
    "id": "ML5PH",
    "label": "5 💎",
    "price": "12",
    "product": "MLBB",
    "status": "active",
        "sp": 1

  },
    {
    "id": "ML11PH",
    "label": "10+1 💎",
    "price": "18",
    "product": "MLBB",
    "status": "active",
        "sp": 1

  },
      {
    "id": "ML22PH",
    "label": "20+2 💎",
    "price": "36",
    "product": "MLBB",
    "status": "active",
        "sp": 1

  }
]